LICENSE
README.md
flask_pack.py
setup.py
Flask_utils_pack.egg-info/PKG-INFO
Flask_utils_pack.egg-info/SOURCES.txt
Flask_utils_pack.egg-info/dependency_links.txt
Flask_utils_pack.egg-info/requires.txt
Flask_utils_pack.egg-info/top_level.txt